arcade_mailchimp_marketing_api/__init__.py
arcade_mailchimp_marketing_api/moar/Mailchimp_Marketing.json
arcade_mailchimp_marketing_api/moar/openapi.json
arcade_mailchimp_marketing_api/tools/__init__.py
arcade_mailchimp_marketing_api/tools/request_body_schemas.py
arcade_mailchimp_marketing_api/tools/utils.py
arcade_mailchimp_marketing_api/wrapper_tools/AddAudienceMergeField.json
arcade_mailchimp_marketing_api/wrapper_tools/AddCampaignFeedback.json
arcade_mailchimp_marketing_api/wrapper_tools/AddCartToStore.json
arcade_mailchimp_marketing_api/wrapper_tools/AddCustomerToStore.json
arcade_mailchimp_marketing_api/wrapper_tools/AddLineItemToCart.json
arcade_mailchimp_marketing_api/wrapper_tools/AddListMemberEvent.json
arcade_mailchimp_marketing_api/wrapper_tools/AddMemberToMailchimpList.json
arcade_mailchimp_marketing_api/wrapper_tools/AddMemberToStaticSegment.json
arcade_mailchimp_marketing_api/wrapper_tools/AddNewEcommerceStore.json
arcade_mailchimp_marketing_api/wrapper_tools/AddNoteToSubscriber.json
arcade_mailchimp_marketing_api/wrapper_tools/AddOrUpdateCustomerInStore.json
arcade_mailchimp_marketing_api/wrapper_tools/AddOrUpdateListMember.json
arcade_mailchimp_marketing_api/wrapper_tools/AddOrderLineItem.json
arcade_mailchimp_marketing_api/wrapper_tools/AddOrderToStore.json
arcade_mailchimp_marketing_api/wrapper_tools/AddProductImage.json
arcade_mailchimp_marketing_api/wrapper_tools/AddProductToStore.json
arcade_mailchimp_marketing_api/wrapper_tools/AddProductVariantMailchimp.json
arcade_mailchimp_marketing_api/wrapper_tools/AddPromoCodeToStore.json
arcade_mailchimp_marketing_api/wrapper_tools/AddStorePromoRule.json
arcade_mailchimp_marketing_api/wrapper_tools/AddSubscriberToWorkflow.json
arcade_mailchimp_marketing_api/wrapper_tools/AddVerifiedDomain.json
arcade_mailchimp_marketing_api/wrapper_tools/ArchiveContactMailchimp.json
arcade_mailchimp_marketing_api/wrapper_tools/ArchiveListMember.json
arcade_mailchimp_marketing_api-1.0.0.dist-info/METADATA
arcade_mailchimp_marketing_api-1.0.0.dist-info/WHEEL
arcade_mailchimp_marketing_api-1.0.0.dist-info/entry_points.txt
arcade_mailchimp_marketing_api-1.0.0.dist-info/licenses/LICENSE
arcade_mailchimp_marketing_api-1.0.0.dist-info/RECORD
